{"cameraMode":{"drawMode":0,"name":"Shaded","section":"Shading Mode"},"sceneLighting":true,"audioPlay":false,"sceneViewState":{"m_AlwaysRefresh":false,"showFog":true,"showSkybox":true,"showFlares":true,"showImageEffects":true,"showParticleSystems":true,"showVisualEffectGraphs":true,"m_FxEnabled":true},"in2DMode":false,"pivot":{"x":-20.05499267578125,"y":-20.229602813720704,"z":130.5738525390625},"rotation":{"x":0.08018118888139725,"y":-0.9198194146156311,"z":0.27338263392448428,"w":0.26978063583374026},"size":183.390625,"orthographic":true}